[
  {
    "id": 1,
    "title": "Tolq",
    "description": "Tolq is the translation solution built for e-commerce. It provides all pieces of the localization puzzle in one single integrated solution.",
    "image": "tolq-image",
    "link": "/"
  },
  {
    "id": 2,
    "title": "Feedback Labs",
    "description": "Feedback Labs turns feedback into actionable insights for your team.",
    "image": "feedback-image",
    "link": "/"
  },
  {
    "id": 3,
    "title": "Codekeeper",
    "description": "Codekeeper is an all-in-one solution for software developers and publishers to provide source code escrow as part of service level and license agreements.",
    "image": "codekeeper-image",
    "link": "/"
  },
  {
    "id": 4,
    "title": "LegalSite",
    "description": "Protected against legal risks, privacy compliant and always up-to-date with the latest regulatory developments.",
    "image": "legal-image",
    "link": "/"
  }
]